np_chaonay/__init__.py
np_chaonay/main.py
np_chaonay/math.py
np_chaonay/humour/__init__.py
np_chaonay/humour/main.py
np_chaonay-1.3.0.dist-info/LICENSE
np_chaonay-1.3.0.dist-info/METADATA
np_chaonay-1.3.0.dist-info/WHEEL
np_chaonay-1.3.0.dist-info/top_level.txt
np_chaonay-1.3.0.dist-info/RECORD
