Metadata-Version: 2.1
Name: np-chaonay
Version: 1.3.0
Summary: Objects collection package by NP-chaonay
Home-page: https://github.com/NP-chaonay/PythonPkg-np_chaonay
Author: Nuttapong Punpipat
Author-email: nuttapongpunpipat@gmail.com
License: UNKNOWN
Platform: UNKNOWN
Classifier: Topic :: Other/Nonlisted Topic
Classifier: Development Status :: 5 - Production/Stable
Classifier: License :: Other/Proprietary License
Classifier: Programming Language :: Python :: 3 :: Only
Classifier: Operating System :: OS Independent
Classifier: Natural Language :: English
Requires-Python: >=3.0
